odoo/addons/remaining_days_widget_reformat_state/README.rst
odoo/addons/remaining_days_widget_reformat_state/__init__.py
odoo/addons/remaining_days_widget_reformat_state/__manifest__.py
odoo/addons/remaining_days_widget_reformat_state/readme/CONTRIBUTORS.rst
odoo/addons/remaining_days_widget_reformat_state/readme/DESCRIPTION.rst
odoo/addons/remaining_days_widget_reformat_state/readme/USAGE.rst
odoo/addons/remaining_days_widget_reformat_state/static/description/icon.png
odoo/addons/remaining_days_widget_reformat_state/static/description/index.html
odoo/addons/remaining_days_widget_reformat_state/static/src/js/remaining_days_widget_reformat_state.js
odoo/addons/remaining_days_widget_reformat_state/templates/assets.xml
odoo14_addon_remaining_days_widget_reformat_state-14.0.1.0.1.dev1.dist-info/METADATA
odoo14_addon_remaining_days_widget_reformat_state-14.0.1.0.1.dev1.dist-info/WHEEL
odoo14_addon_remaining_days_widget_reformat_state-14.0.1.0.1.dev1.dist-info/top_level.txt
odoo14_addon_remaining_days_widget_reformat_state-14.0.1.0.1.dev1.dist-info/RECORD
