Metadata-Version: 2.1
Name: odoo14-addon-remaining_days_widget_reformat_state
Version: 14.0.1.0.1.dev1
Summary: Reformat text shown with remaining_days widget
Home-page: https://www.sygel.es
Author: Sygel, Odoo Community Association (OCA)
Author-email: support@odoo-community.org
Classifier: Programming Language :: Python
Classifier: Framework :: Odoo
Classifier: Framework :: Odoo :: 14.0
Requires-Python: >=3.6
Requires-Dist: odoo<14.1dev,>=14.0a
